DLex/GrParser.py
DLex/LexIO.py
DLex/ReParser.py
DLex/__init__.py
DLex/cli.py
DLex/genfa.py
DLex/lexer.py
DLex_DeaL-0.0.3.dist-info/LICENSE
DLex_DeaL-0.0.3.dist-info/METADATA
DLex_DeaL-0.0.3.dist-info/WHEEL
DLex_DeaL-0.0.3.dist-info/top_level.txt
DLex_DeaL-0.0.3.dist-info/RECORD
