Metadata-Version: 2.1
Name: DLex-DeaL
Version: 0.0.3
Summary: DL's Lex
Home-page: https://github.com/dailing57/DLex
Author: Dai Ling
Author-email: dialing57@163.com
License: UNKNOWN
Project-URL: Bug Tracker, https://github.com/dailing57/DLex/issues
Platform: UNKNOWN
Classifier: Programming Language :: Python :: 3
Classifier: License :: OSI Approved :: MIT License
Classifier: Operating System :: OS Independent
Requires-Python: >=3.6
